[
    {
        "Id": 1,
        "TagLabel": "进攻型"
    },
    {
        "Id": 2,
        "TagLabel": "装甲型"
    },
    {
        "Id": 3,
        "TagLabel": "辅助型"
    },
    {
        "Id": 4,
        "TagLabel": "先锋型"
    },
    {
        "Id": 5,
        "TagLabel": "物理"
    },
    {
        "Id": 6,
        "TagLabel": "火"
    },
    {
        "Id": 7,
        "TagLabel": "物理"
    },
    {
        "Id": 8,
        "TagLabel": "雷"
    },
    {
        "Id": 9,
        "TagLabel": "暗"
    },
    {
        "Id": 10,
        "TagLabel": "冰"
    },
    {
        "Id": 11,
        "TagLabel": "工程部队"
    },
    {
        "Id": 12,
        "TagLabel": "清理部队"
    },
    {
        "Id": 13,
        "TagLabel": "遗忘者小队"
    },
    {
        "Id": 14,
        "TagLabel": "灰鸦小队"
    },
    {
        "Id": 15,
        "TagLabel": "升格者"
    },
    {
        "Id": 16,
        "TagLabel": "突击鹰小队"
    },
    {
        "Id": 17,
        "TagLabel": "守林人"
    },
    {
        "Id": 18,
        "TagLabel": "阿迪莱商会"
    },
    {
        "Id": 19,
        "TagLabel": "艺术协会"
    },
    {
        "Id": 20,
        "TagLabel": "无从属"
    },
    {
        "Id": 21,
        "TagLabel": "三头犬小队"
    },
    {
        "Id": 22,
        "TagLabel": "特遣区"
    },
    {
        "Id": 23,
        "TagLabel": "九龙商会"
    },
    {
        "Id": 24,
        "TagLabel": "考古小队"
    },
    {
        "Id": 25,
        "TagLabel": "好胜心"
    },
    {
        "Id": 26,
        "TagLabel": "坚贞信仰"
    },
    {
        "Id": 27,
        "TagLabel": "铭记"
    },
    {
        "Id": 28,
        "TagLabel": "灰鸦的刀刃"
    },
    {
        "Id": 29,
        "TagLabel": "机车大师"
    },
    {
        "Id": 30,
        "TagLabel": "精密计算"
    },
    {
        "Id": 31,
        "TagLabel": "代行者"
    },
    {
        "Id": 32,
        "TagLabel": "法奥斯毕业生"
    },
    {
        "Id": 33,
        "TagLabel": "大智若愚"
    },
    {
        "Id": 34,
        "TagLabel": "异人型领袖"
    },
    {
        "Id": 35,
        "TagLabel": "四功五法"
    },
    {
        "Id": 36,
        "TagLabel": "富有画家"
    },
    {
        "Id": 37,
        "TagLabel": "圣洁"
    },
    {
        "Id": 38,
        "TagLabel": "困"
    },
    {
        "Id": 39,
        "TagLabel": "会造萝卜"
    },
    {
        "Id": 40,
        "TagLabel": "田园猫"
    },
    {
        "Id": 41,
        "TagLabel": "瓦尔基里"
    },
    {
        "Id": 42,
        "TagLabel": "暴风雨"
    },
    {
        "Id": 43,
        "TagLabel": "好胃口"
    },
    {
        "Id": 44,
        "TagLabel": "九龙之意志"
    },
    {
        "Id": 45,
        "TagLabel": "好奇心"
    },
    {
        "Id": 46,
        "TagLabel": "机械舞"
    },
    {
        "Id": 47,
        "TagLabel": "怪力"
    },
    {
        "Id": 48,
        "TagLabel": "演员"
    },
    {
        "Id": 49,
        "TagLabel": "增幅型"
    }
]