[
    {
        "Id": 1,
        "Name": "完成节点数",
        "Factor": [
            3.0
        ]
    },
    {
        "Id": 2,
        "Name": "完成战斗节点数",
        "Factor": [
            2.0
        ]
    },
    {
        "Id": 3,
        "Name": "完成章节数",
        "Factor": [
            30.0,
            70.0,
            120.0,
            180.0,
            250.0,
            330.0
        ]
    },
    {
        "Id": 4,
        "Name": "套装数",
        "Factor": [
            3.0
        ]
    },
    {
        "Id": 5,
        "Name": "装备数",
        "Factor": [
            1.0
        ]
    },
    {
        "Id": 6,
        "Name": "藏品数",
        "Factor": [
            2.0
        ]
    }
]